Sequential circuits/Registers/N-bit Ring and Johnson Counter/ncounters.sv
//Code to test N-bit Ring counters and Johnson counters
module n_ring_johnson #(parameter N=4)
(
 input logic clk,rst,
 input logic opcode,    //Block to describe the simulation of N-bit universal shift register 
                         //Inputs clock,reset and enable 
 output logic[N-1:0]q        //Array DFF inputs similarly for output
 );                         //opcode array to enable selection in multiplexer containing 4 operations HOLD,LS,RS and //el loading 
 
 always_ff @(posedge clk or posedge rst)begin
 if (rst) begin
    q<='0;
    q[0]<=1'b1;  //Sets an initial state for the counters to start from.
    end
else
begin case(opcode)
    
     
     1'b0:  //ring OP:- 0001,0010,0100,1000,0001
     begin 
     for(int i=0;i<N-1;i++)
         q[i]<=q[i+1];
         
    q[N-1]<=q[0];
    end
     
     1'b1:  //johnson Op:- 0001,0011,0111,1111,1110,1100,1000,0001
     begin
      for(int i=0;i<N-1;i++)
         q[i]<=q[i+1];
         
    q[N-1]<= ~q[0];
    end
    endcase
 end
 end
 endmodule

Sequential circuits/Registers/N-bit Ring and Johnson Counter/n_ring_johnsontest.sv
module counters;
parameter N=4;
logic clk,rst;
logic [N-1:0]q;
logic opcode;

n_ring_johnson #(.N(N)) uut(
   .q(q),
   .clk(clk),
   .rst(rst),
   .opcode(opcode)  
);

initial begin
   clk=0;
   forever #5 clk = ~clk;
    end
    
    initial begin
    $dumpfile("n_ring_johnson.vcd");
    $dumpvars(0,counters);
    
    end
    initial begin
         $monitor("Time=%0t | rst=%b | opcode=%b | q=%b",
              $time, rst, opcode, q);
    end
    
     initial begin

         // Initialize all inputs
    rst = 1;
    opcode = 1'b0;
    
    // Reset
    #10;
    rst = 0;  
        
        opcode = 1'b0;   //Ring counter
        #40;
        rst=1;
        #10;
        rst=0;
        opcode = 1'b1;   //johnson counter
        #80;
        
           $finish;
        end
     
        endmodule

Sequential circuits/Registers/N-bit Ring and Johnson Counter/n_ring_johnson.vcd
$date
	Tue Jul 28 23:08:27 2026
$end
$version
	Icarus Verilog
$end
$timescale
	1s
$end
$scope module counters $end
$var wire 4 ! q [3:0] $end
$var parameter 32 " N $end
$var reg 1 # clk $end
$var reg 1 $ opcode $end
$var reg 1 % rst $end
$scope module uut $end
$var wire 1 # clk $end
$var wire 1 $ opcode $end
$var wire 1 % rst $end
$var parameter 32 & N $end
$var reg 4 ' q [3:0] $end
$scope begin $ivl_for_loop0 $end
$var integer 32 ( i [31:0] $end
$upscope $end
$scope begin $ivl_for_loop1 $end
$var integer 32 ) i [31:0] $end
$upscope $end
$upscope $end
$upscope $end
$enddefinitions $end
$comment Show the parameter values. $end
$dumpall
b100 &
b100 "
$end
#0
$dumpvars
b0 )
b0 (
b1 '
1%
0$
0#
b1 !
$end
#5
b1 !
b1 '
1#
#10
0#
0%
#15
b1000 !
b1000 '
b11 (
1#
#20
0#
#25
b100 !
b100 '
b11 (
1#
#30
0#
#35
b10 !
b10 '
b11 (
1#
#40
0#
#45
b1 !
b1 '
b11 (
1#
#50
b1 !
b1 '
0#
1%
#55
b1 !
b1 '
1#
#60
0#
1$
0%
#65
b0 !
b0 '
b11 )
1#
#70
0#
#75
b1000 !
b1000 '
b11 )
1#
#80
0#
#85
b1100 !
b1100 '
b11 )
1#
#90
0#
#95
b1110 !
b1110 '
b11 )
1#
#100
0#
#105
b1111 !
b1111 '
b11 )
1#
#110
0#
#115
b111 !
b111 '
b11 )
1#
#120
0#
#125
b11 !
b11 '
b11 )
1#
#130
0#
#135
b1 !
b1 '
b11 )
1#
