ALU /ALU-4bit/alu_4bit.v
module alu_4bit (
    input  [3:0] A,
    input  [3:0] B,
    input  [1:0] opcode,
    output reg [3:0] Result,
    output reg C,   // Carry/Borrow
    output reg Z,   // Zero
    output reg S,   // Sign
    output reg V    // Overflow
);

    // Internal wires
    wire [4:0] add_temp; // Temporary 5-bit to capture carry
    wire [4:0] sub_temp;

    wire [3:0] add_out, sub_out, and_out, or_out;

    // Computes in parallel
    assign add_temp = A + B;
    assign sub_temp = A - B;

    assign add_out = add_temp[3:0]; //Adds the number without the carry to keep it simple 
    assign sub_out = sub_temp[3:0];
    assign and_out = A & B;
    assign or_out  = A | B;

    always @(*) begin
        // Assigning by default
        Result = 4'b0000;
        C = 0;
        V = 0;

        case(opcode)
            2'b00: begin // ADD
                Result = add_out;
                C = add_temp[4]; //Also includes the carry here

                // Overflow detection (signed)
                V = (A[3] == B[3]) && (Result[3] != A[3]);
            end

            2'b01: begin // SUB
                Result = sub_out;
                C = sub_temp[4]; // borrow indication

                // Overflow detection
                V = (A[3] != B[3]) && (Result[3] != A[3]);
            end

            2'b10: begin // AND
                Result = and_out;
                C = 0;
                V = 0;
            end

            2'b11: begin // OR
                Result = or_out;
                C = 0;
                V = 0;
            end
        endcase

        // Common flags
        Z = (Result == 4'b0000);
        S = Result[3];

    end

endmodule

ALU /ALU-4bit/alu_4bittest.v
module alu_4bit_tb;

    reg [3:0] A, B;
    reg [1:0] opcode;

    wire [3:0] Result;
    wire C, Z, S, V;

    // Instantiate ALU
    alu_4bit uut (
        .A(A),
        .B(B),
        .opcode(opcode),
        .Result(Result),
        .C(C),
        .Z(Z),
        .S(S),
        .V(V)
    );

    initial begin
        $dumpfile("alu.vcd");
        $dumpvars(0, alu_4bit_tb);

        // ADD
        A = 4'b0101; B = 4'b0011; opcode = 2'b00; #10;
        A = 4'b1111; B = 4'b0001; opcode = 2'b00; #10;

        // SUB
        A = 4'b0101; B = 4'b0011; opcode = 2'b01; #10;
        A = 4'b0011; B = 4'b0101; opcode = 2'b01; #10;

        // AND
        A = 4'b1100; B = 4'b1010; opcode = 2'b10; #10;

        // OR
        A = 4'b1100; B = 4'b1010; opcode = 2'b11; #10;

        // ZERO case
        A = 4'b0000; B = 4'b0000; opcode = 2'b00; #10;

        // SIGN test
        A = 4'b1000; B = 4'b0001; opcode = 2'b01; #10;

        #10 $finish;
    end

endmodule

ALU /ALU-4bit/alu.vcd
$date
	Fri May  1 19:12:29 2026
$end
$version
	Icarus Verilog
$end
$timescale
	1s
$end
$scope module alu_4bit_tb $end
$var wire 1 ! Z $end
$var wire 1 " V $end
$var wire 1 # S $end
$var wire 4 $ Result [3:0] $end
$var wire 1 % C $end
$var reg 4 & A [3:0] $end
$var reg 4 ' B [3:0] $end
$var reg 2 ( opcode [1:0] $end
$scope module uut $end
$var wire 4 ) A [3:0] $end
$var wire 4 * B [3:0] $end
$var wire 4 + and_out [3:0] $end
$var wire 2 , opcode [1:0] $end
$var wire 4 - or_out [3:0] $end
$var wire 5 . sub_temp [4:0] $end
$var wire 4 / sub_out [3:0] $end
$var wire 5 0 add_temp [4:0] $end
$var wire 4 1 add_out [3:0] $end
$var reg 1 % C $end
$var reg 4 2 Result [3:0] $end
$var reg 1 # S $end
$var reg 1 " V $end
$var reg 1 ! Z $end
$upscope $end
$upscope $end
$enddefinitions $end
$comment Show the parameter values. $end
$dumpall
$end
#0
$dumpvars
b1000 2
b1000 1
b1000 0
b10 /
b10 .
b111 -
b0 ,
b1 +
b11 *
b101 )
b0 (
b11 '
b101 &
0%
b1000 $
1#
1"
0!
$end
#10
0#
1!
b1111 -
b0 1
b1110 /
1%
0"
b0 $
b0 2
b1 '
b1 *
b10000 0
b1110 .
b1111 &
b1111 )
#20
b111 -
b1000 1
b10 /
0#
0!
b10 $
b10 2
0%
b1 (
b1 ,
b11 '
b11 *
b1000 0
b10 .
b101 &
b101 )
#30
1#
b1110 /
1%
b1110 $
b1110 2
b101 '
b101 *
b1000 0
b11110 .
b11 &
b11 )
#40
b1000 +
b1110 -
b110 1
b10 /
1#
0%
b1000 $
b1000 2
b10 (
b10 ,
b1010 '
b1010 *
b10110 0
b10 .
b1100 &
b1100 )
#50
b1110 $
b1110 2
b11 (
b11 ,
#60
1!
b0 +
b0 -
b0 1
b0 /
0#
b0 $
b0 2
b0 (
b0 ,
b0 '
b0 *
b0 0
b0 .
b0 &
b0 )
#70
0!
b111 $
b111 2
b1001 -
b1001 1
b111 /
1"
b1 (
b1 ,
b1 '
b1 *
b1001 0
b111 .
b1000 &
b1000 )
