ALU /N-BIT MOD ALU/n_bitcompare.v
module comparator #(parameter N = 4)(
    input  [N-1:0] A,
    input  [N-1:0] B,
    output reg G,
    output reg L,
    output reg E
);

integer i;

always @(*) begin : COMPARE_BLOCK
    G  = 0;
    L  = 0;
    E = 0;

    for (i = N-1; i >= 0; i = i - 1) begin
        
        if (A[i] > B[i]) begin
            G = 1;
            disable COMPARE_BLOCK;
        end
        
        else if (A[i] < B[i]) begin
            L = 1;
            disable COMPARE_BLOCK;
        end
    end

    // If loop completes → equal
    E = 1;
end

endmodule

ALU /N-BIT MOD ALU/mod_alu.v
module n_mod_alu #(parameter N = 4)(

    input  [N-1:0] A,
    input  [N-1:0] B,

    //Does the main Operation Select among Arithmetic,Logical ,Shift or compare 
   
    input [1:0] op_main,

  
    input [1:0] op_ar,      //Selects the 2 arithmetic operations 0->ADD 1->SUB
    input [1:0] op_log,      // Selects the logical operations like AND,OR,XOR etc
    input [1:0] op_shift,    // Selects the shifting operations Left,Right,Arithmetic

    output reg [N-1:0] Result, //Since index starts from 0 we go upto n-1 bits only

    // Flags
    output reg C,Z,S,V,   //C-Carry ,S-Sign ,Z-Zero,V-Overflow

    // Separate flags for Comparator outputs:-Lesser(L),Greater(G),Equal(E)
    output L,E,G

);

    // Sets temporary wires (Processing) to tackle Carry/Borrow 
    
    wire [N:0] add_temp;
    wire [N:0] sub_temp;
    
    //Sets output wires for arithmetic operations
    wire [N-1:0] add_out,sub_out,mult_out,div_out;
    
    //Sets output wires for Logical operations
    wire [N-1:0] and_out,or_out,xor_out;
    
   //Sets output wires for Shifting operations
    wire [N-1:0] left_shift_out,right_shift_out,arith_shift_out;


    // Arithmetic
    assign add_temp = A + B;
    assign sub_temp = A - B;
    
    assign add_out = add_temp[N-1:0];//Assigning the temp wire expression for full expression with carry
    assign sub_out = sub_temp[N-1:0];
    assign mult_out= A*B;
    assign div_out= (B!=0)?(A/B):0; //Prevents division by zero by returning 0 when B=0

    // Logical
    assign and_out = A & B;
    assign or_out  = A | B;
    assign xor_out = A ^ B;

    // Shift
    assign left_shift_out  = A << 1; //Shifts to the left by 1 bit by inserting 0 in LSB
    assign right_shift_out = A >> 1; //Shifts to the right by 1 bit by inseritng 0 in MSB

    // Arithmetic Right Shift
    assign arith_shift_out = $signed(A) >>> 1; //Shifts right and replicates the sign bit by preserving the sign bit 

    // Comparator

    comparator #(N) comp1(

        .A(A),
        .B(B),

        .L(L),
        .E(E),
        .G(G)

    );             //Uses the external N-bit comparator module saved in the same folder as this


    always @(*) begin

        // Default values
        Result = 0;

        C = 0;
        V = 0;

        // Main operations select

        case(op_main)

            // Arithmetic

            2'b00: begin

                case(op_ar)//Selects the sub ops ADD/SUB

                    // ADD
                    2'b00: begin
                        Result = add_out;
                        C = add_temp[N];

                        // Overflow Logic
                        V = (A[N-1] == B[N-1]) &&
                            (Result[N-1] != A[N-1]);
                    end

                    // SUBTRACT
                    2'b01: begin
                        Result = sub_out;
                        C = sub_temp[N];
                        // Overflow Logic
                        V = (A[N-1] != B[N-1]) &&
                            (Result[N-1] != A[N-1]);

                    end
                  2'b10:begin
                  Result=mult_out;
                  end
                  
                  2'b11:begin
                  Result=div_out;
                  end
                endcase

            end

            // Logical

            2'b01: begin

                case(op_log)//Selects AND,OR,XOR etc

                    2'b00: Result = and_out;
                    2'b01: Result = or_out;
                    2'b10: Result = xor_out;

                    default: Result = 0;

                endcase

            end

            // Shift ops
            
            2'b10: begin

                case(op_shift)//Selects the SUB SHIFT operations LS,RS,ARS

                    2'b00: Result = left_shift_out;
                    2'b01: Result = right_shift_out;
                    2'b10: Result = arith_shift_out;

                    default: Result = 0;

                endcase

            end

            // Compare

            2'b11: begin

                // Since omparator outputs handled separately
                Result = 0;

            end

            default: begin

                Result = 0;

            end

        endcase

    
        // COMMON FLAGS

        Z = (Result == 0);

        S = Result[N-1];

    end

endmodule

ALU /N-BIT MOD ALU/n_mod_alutest.v


module test_modular_alu;
    parameter N = 4;
    reg [N-1:0] A;
    reg [N-1:0] B;

    // Main Opcode
    reg [1:0] op_main;

    // Sub-opcodes
    reg  [1:0] op_ar;
    reg [1:0]  op_log;
    reg [1:0]  op_shift;
    wire [N-1:0] Result;
    wire C;
    wire Z;
    wire S;
    wire V;

    // Comparator Outputs
    wire L;
    wire E;
    wire G;

    n_mod_alu #(N) uut (

        .A(A),
        .B(B),

        .op_main(op_main),

        .op_ar(op_ar),
        .op_log(op_log),
        .op_shift(op_shift),

        .Result(Result),

        .C(C),
        .Z(Z),
        .S(S),
        .V(V),

        .L(L),
        .E(E),
        .G(G)

    );

   

    initial begin
       
        // Waveform dump
        $dumpfile("mod_alu.vcd");
        $dumpvars(0, test_modular_alu);
        A=0;
        B=0;
        op_main=0;
        op_ar=0;
        op_shift=0;
        op_log=0;
        #5
        // ARITHMETIC OPERATIONS
     
        // ADD : 5 + 3 = 8
        A = 4'd5;
        B = 4'd3;
        op_main = 2'b00;
        op_ar   = 2'b00;
        #5;

        // SUB : 5 - 3 = 2
        A = 4'd5;
        B = 4'd3;
        op_main = 2'b00;
        op_ar  = 2'b01;
        #5;
        
        //Multiplication
         A = 4'd5;
        B = 4'd3;
        op_main=2'b00;
        op_ar=2'b10;
        #5;
        
        //Division
         A = 4'd5;
        B = 4'd3;
        op_main=2'b00;
        op_ar=2'b11;
        #5;
        // LOGICAL OPERATIONS

        // AND
        A = 4'd5;
        B = 4'd3;

        op_main = 2'b01;
        op_log  = 2'b00;

        #5;

        // OR
        A = 4'd3;
        B = 4'd3;

        op_main = 2'b01;
        op_log  = 2'b01;

        #5;

        // XOR
        A = 4'd5;
        B = 4'd3;

        op_main = 2'b01;
        op_log  = 2'b10;

        #5;

        // SHIFT OPERATIONS

        // LEFT SHIFT
        A = 4'd5;

        op_main  = 2'b10;
        op_shift = 2'b00;

        #5;

        // RIGHT SHIFT
        A = 4'd5;

        op_main  = 2'b10;
        op_shift = 2'b01;

        #5;

        // ARITHMETIC SHIFT
        A = 4'd5;

        op_main  = 2'b10;
        op_shift = 2'b10;

        #5;
        // COMPARATOR OPERATIONS


        A = 4'd9;
        B = 4'd4;

        op_main = 2'b11;

        #5;


        $finish;

    end

endmodule

ALU /N-BIT MOD ALU/n_bitcomparetest.v
module test;

parameter N = 4;

reg  [N-1:0] A, B;
wire G, L, E;

// Instantiate comparator
comparator #(N) uut (
    .A(A),
    .B(B),
    .G(G),
    .L(L),
    .E(E)
);

initial begin
    $dumpfile("wave.vcd");
    $dumpvars(0, test);

    // Test cases

    A = 4'b1010; B = 4'b1001; #10; // A > B
    A = 4'b0011; B = 4'b0100; #10; // A < B
    A = 4'b0111; B = 4'b0111; #10; // A == B
    A = 4'b0000; B = 4'b1111; #10; // A < B
    A = 4'b1111; B = 4'b0000; #10; // A > B

    #10 $finish;
end

endmodule

ALU /N-BIT MOD ALU/wave.vcd
$date
	Sat May  9 11:49:31 2026
$end
$version
	Icarus Verilog
$end
$timescale
	1s
$end
$scope module test $end
$var wire 1 ! L $end
$var wire 1 " G $end
$var wire 1 # E $end
$var parameter 32 $ N $end
$var reg 4 % A [3:0] $end
$var reg 4 & B [3:0] $end
$scope module uut $end
$var wire 4 ' A [3:0] $end
$var wire 4 ( B [3:0] $end
$var parameter 32 ) N $end
$var reg 1 # E $end
$var reg 1 " G $end
$var reg 1 ! L $end
$var integer 32 * i [31:0] $end
$scope begin COMPARE_BLOCK $end
$upscope $end
$upscope $end
$upscope $end
$scope module test_modular_alu $end
$var wire 1 + Z $end
$var wire 1 , V $end
$var wire 1 - S $end
$var wire 4 . Result [3:0] $end
$var wire 1 / L $end
$var wire 1 0 G $end
$var wire 1 1 E $end
$var wire 1 2 C $end
$var parameter 32 3 N $end
$var reg 4 4 A [3:0] $end
$var reg 4 5 B [3:0] $end
$var reg 2 6 op_ar [1:0] $end
$var reg 2 7 op_log [1:0] $end
$var reg 2 8 op_main [1:0] $end
$var reg 2 9 op_shift [1:0] $end
$scope module uut $end
$var wire 4 : A [3:0] $end
$var wire 4 ; B [3:0] $end
$var wire 4 < and_out [3:0] $end
$var wire 2 = op_ar [1:0] $end
$var wire 2 > op_log [1:0] $end
$var wire 2 ? op_main [1:0] $end
$var wire 2 @ op_shift [1:0] $end
$var wire 4 A or_out [3:0] $end
$var wire 4 B xor_out [3:0] $end
$var wire 5 C sub_temp [4:0] $end
$var wire 4 D sub_out [3:0] $end
$var wire 4 E right_shift_out [3:0] $end
$var wire 4 F mult_out [3:0] $end
$var wire 4 G left_shift_out [3:0] $end
$var wire 4 H div_out [3:0] $end
$var wire 4 I arith_shift_out [3:0] $end
$var wire 5 J add_temp [4:0] $end
$var wire 4 K add_out [3:0] $end
$var wire 1 / L $end
$var wire 1 0 G $end
$var wire 1 1 E $end
$var parameter 32 L N $end
$var reg 1 2 C $end
$var reg 4 M Result [3:0] $end
$var reg 1 - S $end
$var reg 1 , V $end
$var reg 1 + Z $end
$scope module comp1 $end
$var wire 4 N A [3:0] $end
$var wire 4 O B [3:0] $end
$var parameter 32 P N $end
$var reg 1 1 E $end
$var reg 1 0 G $end
$var reg 1 / L $end
$var integer 32 Q i [31:0] $end
$scope begin COMPARE_BLOCK $end
$upscope $end
$upscope $end
$upscope $end
$upscope $end
$enddefinitions $end
$comment Show the parameter values. $end
$dumpall
b100 P
b100 L
b100 3
b100 )
b100 $
$end
#0
$dumpvars
b11111111111111111111111111111111 Q
b0 O
b0 N
b0 M
b0 K
b0 J
b0 I
b0 H
b0 G
b0 F
b0 E
b0 D
b0 C
b0 B
b0 A
b0 @
b0 ?
b0 >
b0 =
b0 <
b0 ;
b0 :
b0 9
b0 8
b0 7
b0 6
b0 5
b0 4
02
11
00
0/
b0 .
0-
0,
1+
b1 *
b1001 (
b1010 '
b1001 &
b1010 %
0#
1"
0!
$end
#5
b1 H
1-
0+
1,
b1000 .
b1000 M
b1 <
b111 A
b110 B
b1000 K
b10 D
b1010 G
b10 E
b10 I
10
b10 Q
01
b1111 F
b11 5
b11 ;
b11 O
b1000 J
b10 C
b101 4
b101 :
b101 N
#10
0-
0,
b10 .
b10 M
1!
b10 *
0"
b1 6
b1 =
b100 &
b100 (
b11 %
b11 '
#15
1-
b1111 .
b1111 M
b10 6
b10 =
#20
0-
b1 .
b1 M
1#
b11111111111111111111111111111111 *
0!
b11 6
b11 =
b111 &
b111 (
b111 %
b111 '
#25
b1 .
b1 M
b1 8
b1 ?
#30
b11 <
b11 A
b0 B
b110 K
b0 D
b110 G
b1 E
b1 I
11
b11111111111111111111111111111111 Q
00
b11 .
b11 M
1!
b11 *
0#
b1 7
b1 >
b110 J
b0 C
b1001 F
b11 4
b11 :
b11 N
b1111 &
b1111 (
b0 %
b0 '
#35
b1 <
b111 A
b110 B
b1000 K
b10 D
b1010 G
b10 E
b10 I
10
b10 Q
01
0+
b110 .
b110 M
b10 7
b10 >
b1000 J
b10 C
b1111 F
b101 4
b101 :
b101 N
#40
1-
b1010 .
b1010 M
1"
0!
b10 8
b10 ?
b0 &
b0 (
b1111 %
b1111 '
#45
0-
b10 .
b10 M
b1 9
b1 @
#50
b10 .
b10 M
b10 9
b10 @
#55
b10 H
b0 <
b1101 A
b1101 B
b1101 K
b101 D
b10 G
b100 E
b1100 I
b11 Q
10
1+
b0 .
b0 M
b11 8
b11 ?
b100 5
b100 ;
b100 O
b1101 J
b101 C
b100 F
b1001 4
b1001 :
b1001 N
