Sequential circuits/D ff/d_ff.sv
module d_ff(
  input logic clk,rst,d,
  output logic q
);

always_ff @(posedge clk)begin
if(rst)
  q<=1'b0;
else
  q<=d;
end

endmodule

Sequential circuits/D ff/d_fftest.sv
module test;
logic clk,rst,d,q;

d_ff uut(
 .clk(clk),
 .rst(rst),
 .d(d),
 .q(q)
);

always #5 clk= ~clk;

initial begin
  $dumpfile("ff.vcd");
  $dumpvars(0,test);
end

initial begin
  clk=0;
  rst=1;
  d=0;

 #10 rst = 0;
 
#10 d=1;
#10 d=0;
#10 d=1;

#10 rst=1;
#10 rst=0;
#10 d=0;

#20 $finish;
end


initial begin
    $monitor("Time=%0t clk=%b rst=%b d=%b q=%b",
             $time, clk, rst, d, q);
end
endmodule

Sequential circuits/D ff/ff.vcd
$date
	Sun Jul 26 12:29:34 2026
$end
$version
	Icarus Verilog
$end
$timescale
	1s
$end
$scope module test $end
$var wire 1 ! q $end
$var reg 1 " clk $end
$var reg 1 # d $end
$var reg 1 $ rst $end
$scope module uut $end
$var wire 1 " clk $end
$var wire 1 # d $end
$var wire 1 $ rst $end
$var reg 1 ! q $end
$upscope $end
$upscope $end
$enddefinitions $end
$comment Show the parameter values. $end
$dumpall
$end
#0
$dumpvars
1$
0#
0"
x!
$end
#5
0!
1"
#10
0"
0$
#15
1"
#20
0"
1#
#25
1!
1"
#30
0"
0#
#35
0!
1"
#40
0"
1#
#45
1!
1"
#50
0"
1$
#55
0!
1"
#60
0"
0$
#65
1!
1"
#70
0"
0#
#75
0!
1"
