Sequential circuits/Registers/MOD-N counters/mod_n.sv
module mod_n_counter #(
    parameter N = 10,
    parameter WIDTH = 4
)(
    input logic clk,
    input logic rst,
    output logic [WIDTH-1:0] count
);

initial begin
    if ((2**WIDTH) < N) begin
        $display("ERROR: WIDTH is too small for MOD-%0d Counter!", N);
        $finish;
    end
end

always_ff @(posedge clk) begin
    if (rst)
        count <= '0;
    else if (count == N-1)
        count <= '0;
    else
        count <= count + 1;
end

endmodule

Sequential circuits/Registers/MOD-N counters/mod_ncounterstest.sv
module mod_n_counter_tb;

    localparam N = 10;
    localparam WIDTH = 4;

    logic clk;
    logic rst;
    logic [WIDTH-1:0] count;

    // DUT
    mod_n_counter #(
        .N(N),
        .WIDTH(WIDTH)
    ) dut (
        .clk(clk),
        .rst(rst),
        .count(count)
    );

    // Clock Generation
    initial begin
        clk = 0;
        forever #5 clk = ~clk;
    end

    // Dump Waveform
    initial begin
        $dumpfile("mod_ncounters.vcd");
        $dumpvars(0, mod_n_counter_tb);
    end

    // Monitor
    initial begin
        $monitor("Time=%0t | rst=%b | count=%0d",
                 $time, rst, count);
    end

    // Test Sequence
    initial begin
        rst = 1;

        #10;
        rst = 0;

        // Let counter run
        #250;

        // Apply reset again
        rst = 1;
        #10;
        rst = 0;

        #50;

        $finish;
    end

endmodule

Sequential circuits/Registers/MOD-N counters/mod_ncounters.vcd
$date
	Fri Jul 31 16:38:15 2026
$end
$version
	Icarus Verilog
$end
$timescale
	1s
$end
$scope module mod_n_counter_tb $end
$var wire 4 ! count [3:0] $end
$var parameter 32 " N $end
$var parameter 32 # WIDTH $end
$var reg 1 $ clk $end
$var reg 1 % rst $end
$scope module dut $end
$var wire 1 $ clk $end
$var wire 1 % rst $end
$var parameter 32 & N $end
$var parameter 32 ' WIDTH $end
$var reg 4 ( count [3:0] $end
$upscope $end
$upscope $end
$enddefinitions $end
$comment Show the parameter values. $end
$dumpall
b100 '
b1010 &
b100 #
b1010 "
$end
#0
$dumpvars
bx (
1%
0$
bx !
$end
#5
b0 !
b0 (
1$
#10
0$
0%
#15
b1 !
b1 (
1$
#20
0$
#25
b10 !
b10 (
1$
#30
0$
#35
b11 !
b11 (
1$
#40
0$
#45
b100 !
b100 (
1$
#50
0$
#55
b101 !
b101 (
1$
#60
0$
#65
b110 !
b110 (
1$
#70
0$
#75
b111 !
b111 (
1$
#80
0$
#85
b1000 !
b1000 (
1$
#90
0$
#95
b1001 !
b1001 (
1$
#100
0$
#105
b0 !
b0 (
1$
#110
0$
#115
b1 !
b1 (
1$
#120
0$
#125
b10 !
b10 (
1$
#130
0$
#135
b11 !
b11 (
1$
#140
0$
#145
b100 !
b100 (
1$
#150
0$
#155
b101 !
b101 (
1$
#160
0$
#165
b110 !
b110 (
1$
#170
0$
#175
b111 !
b111 (
1$
#180
0$
#185
b1000 !
b1000 (
1$
#190
0$
#195
b1001 !
b1001 (
1$
#200
0$
#205
b0 !
b0 (
1$
#210
0$
#215
b1 !
b1 (
1$
#220
0$
#225
b10 !
b10 (
1$
#230
0$
#235
b11 !
b11 (
1$
#240
0$
#245
b100 !
b100 (
1$
#250
0$
#255
b101 !
b101 (
1$
#260
0$
1%
#265
b0 !
b0 (
1$
#270
0$
0%
#275
b1 !
b1 (
1$
#280
0$
#285
b10 !
b10 (
1$
#290
0$
#295
b11 !
b11 (
1$
#300
0$
#305
b100 !
b100 (
1$
#310
0$
#315
b101 !
b101 (
1$
