Sequential circuits/Registers/Shift register /shift4bit.v
module bit_4shift(
 input logic clk,Din,rst,
 output logic [0:3]q
);

always_ff @(posedge clk)begin
if(rst)
   q<=4'b0000;
else begin
  q[3]<=q[2];
  q[2]<=q[1];
  q[1]<=q[0];
  q[0]<=Din;
end
end
endmodule

Sequential circuits/Registers/Shift register /bit_4test.v


module shift_register_tb;

    logic clk;
    logic rst;
    logic Din;
    logic [3:0] q;

    // DUT
    bit_4shift uut(
        .clk(clk),
        .rst(rst),
        .Din(Din),
        .q(q)
    );

    // Clock Generation (10 ns period)
    initial begin
        clk = 0;
        forever #5 clk = ~clk;
    end

    // Waveform Dump
    initial begin
        $dumpfile("shift_register.vcd");
        $dumpvars(0, shift_register_tb);
    end

    // Monitor Output
    initial begin
        $monitor("Time=%0t | rst=%b | Din=%b | q=%b",
                  $time, rst, Din, q);
    end

    // Test Stimulus
    initial begin

        // Initialize
        rst = 1;
        Din = 0;

        // Reset
        #10;
        rst = 0;

        // Shift in 1
        Din = 1;
        #10;

        // Shift in 0
        Din = 0;
        #10;

        // Shift in 1
        Din = 1;
        #10;

        // Shift in 1
        Din = 1;
        #10;

        // Shift in 0
        Din = 0;
        #10;

        // Shift in 1
        Din = 1;
        #10;

        $finish;

    end

endmodule

Sequential circuits/Registers/Shift register /shift_register.vcd
$date
	Sun Jul 26 15:56:02 2026
$end
$version
	Icarus Verilog
$end
$timescale
	1s
$end
$scope module shift_register_tb $end
$var wire 4 ! q [3:0] $end
$var reg 1 " Din $end
$var reg 1 # clk $end
$var reg 1 $ rst $end
$scope module uut $end
$var wire 1 " Din $end
$var wire 1 # clk $end
$var wire 1 $ rst $end
$var reg 4 % q [0:3] $end
$upscope $end
$upscope $end
$enddefinitions $end
$comment Show the parameter values. $end
$dumpall
$end
#0
$dumpvars
bx %
1$
0#
0"
bx !
$end
#5
b0 !
b0 %
1#
#10
0#
1"
0$
#15
b1000 !
b1000 %
1#
#20
0#
0"
#25
b100 !
b100 %
1#
#30
0#
1"
#35
b1010 !
b1010 %
1#
#40
0#
#45
b1101 !
b1101 %
1#
#50
0#
0"
#55
b110 !
b110 %
1#
#60
0#
1"
#65
b1011 !
b1011 %
1#
