Sequential circuits/Registers/Universal Register/n_universal.sv
//Code to test N-bit modular universal shift register hardware
module n_universal #(parameter N=4)
(
 input logic clk,rst,
 input logic [1:0]opcode,    //Block to describe the simulation of N-bit universal shift register 
 input logic [N-1:0]Din,
 input logic left_shift,right_shift,         //Declares left_shift and right_shift              //Inputs clock,reset and enable 
 output logic[N-1:0]q        //Array DFF inputs similarly for output
 );                         //opcode array to enable selection in multiplexer containing 4 operations HOLD,LS,RS and //el loading 
 
 always_ff @(posedge clk or posedge rst)begin
 if (rst) begin
    q<='0;
    end
else
begin case(opcode)
     2'b00:
     begin
     q<=q; //HOLD
     end
     
     2'b01:  //Right Shift
     begin 
     for(int i=0;i<N-1;i++)
         q[i]<=q[i+1];
         
    q[N-1]<=right_shift;
    end
     
     2'b10:  //Left shift
     begin
     for(int i=N-1;i>0;i--)
        q[i]<=q[i-1];
        
    q[0]<=left_shift;
    end
    
    2'b11: //Parallel input
    begin
    q<=Din;
    end
    
    default:
    begin
    q<=q;
    end
    endcase
 end
 end
 endmodule

Sequential circuits/Registers/Universal Register/n_universaltest.sv
module n_universaltest;

parameter N=4;
logic clk,rst;
logic [N-1:0]Din;
logic [N-1:0]q;
logic [1:0]opcode;
logic left_shift,right_shift;

n_universal #(.N(N)) uut(
   .Din(Din),
   .q(q),
   .clk(clk),
   .rst(rst),
   .opcode(opcode),
   .right_shift(right_shift),
   .left_shift(left_shift)
);

initial begin
   clk=0;
   forever #5 clk = ~clk;
    end
    
    initial begin
    $dumpfile("n_universal.vcd");
    $dumpvars(0,n_universaltest);
    
    end
    initial begin
         $monitor("Time=%0t | rst=%b | opcode=%b | Din=%b | LS=%b | RS=%b | q=%b",
              $time, rst, opcode, Din, left_shift, right_shift, q);
    end
    
     initial begin

         // Initialize all inputs
    rst = 1;
    opcode = 2'b00;
    Din = 4'b0000;
    left_shift = 0;
    right_shift = 0;

    // Reset
    #10;
    rst = 0;
        
        Din = 4'b1011;
        opcode = 2'b11;   //Parallel loading
        #10;
        
        right_shift=0;
        opcode = 2'b01;   //right shift
        #10;
        
        left_shift=0;
        opcode = 2'b10;   //left shift
        #10;
        
        opcode = 2'b00;
        #10;
           $finish;
        end
     
        endmodule

Sequential circuits/Registers/Universal Register/n_universal.vcd
$date
	Tue Jul 28 22:40:38 2026
$end
$version
	Icarus Verilog
$end
$timescale
	1s
$end
$scope module n_universaltest $end
$var wire 4 ! q [3:0] $end
$var parameter 32 " N $end
$var reg 4 # Din [3:0] $end
$var reg 1 $ clk $end
$var reg 1 % left_shift $end
$var reg 2 & opcode [1:0] $end
$var reg 1 ' right_shift $end
$var reg 1 ( rst $end
$scope module uut $end
$var wire 4 ) Din [3:0] $end
$var wire 1 $ clk $end
$var wire 1 % left_shift $end
$var wire 2 * opcode [1:0] $end
$var wire 1 ' right_shift $end
$var wire 1 ( rst $end
$var parameter 32 + N $end
$var reg 4 , q [3:0] $end
$scope begin $ivl_for_loop0 $end
$var integer 32 - i [31:0] $end
$upscope $end
$scope begin $ivl_for_loop1 $end
$var integer 32 . i [31:0] $end
$upscope $end
$upscope $end
$upscope $end
$enddefinitions $end
$comment Show the parameter values. $end
$dumpall
b100 +
b100 "
$end
#0
$dumpvars
b0 .
b0 -
b0 ,
b0 *
b0 )
1(
0'
b0 &
0%
0$
b0 #
b0 !
$end
#5
1$
#10
0$
b11 &
b11 *
b1011 #
b1011 )
0(
#15
b1011 !
b1011 ,
1$
#20
0$
b1 &
b1 *
#25
b101 !
b101 ,
b11 -
1$
#30
0$
b10 &
b10 *
#35
b1010 !
b1010 ,
b0 .
1$
#40
0$
b0 &
b0 *
