ALU /ALU-N bit/alu_nbit.v
module alu_nbit #(parameter N = 4)(
    input  [N-1:0] A,
    input  [N-1:0] B,
    input  [2:0] opcode,
    output reg [N-1:0] Result,
    output reg Z, S, C, V   //V-Overflow logic
);

    // Temporary wires to tackle carries/borrows while computing
    wire [N:0] temp_add;
    wire [N:0] temp_sub;

    wire [N-1:0] add_out, sub_out, and_out, or_out, xor_out;
    wire [N-1:0] left_shift, right_shift, ar_shift;

    // Arithmetic (temp used to tackle carry first here and then stored in add_out)
    assign temp_add = A + B;
    assign temp_sub = A - B;

    assign add_out = temp_add[N-1:0];
    assign sub_out = temp_sub[N-1:0];

    assign and_out = A & B;
    assign or_out  = A | B;
    assign xor_out = A ^ B;

    // Shifts by 1 bit
    assign left_shift  = A << 1;
    assign right_shift  = A >> 1;
    assign ar_shift = $signed(A) >>> 1;

    always @(*) begin
        // default flags
        C = 0;
        V = 0;

        case(opcode)
            3'b000: begin // ADD
                Result = add_out;
                C = temp_add[N];
                V = (A[N-1] == B[N-1]) && (Result[N-1] != A[N-1]);
            end

            3'b001: begin // SUB
                Result = sub_out;
                C = temp_sub[N]; // borrow
                V = (A[N-1] != B[N-1]) && (Result[N-1] != A[N-1]);
            end

            3'b010: Result = and_out;
            3'b011: Result = or_out;
            3'b100: Result = xor_out;
            3'b101: Result = left_shift;
            3'b110: Result = right_shift;
            3'b111: Result = ar_shift;

            default: Result = 0;
        endcase
        Z = (Result == 0);
        S = Result[N-1];  //Sign depends on MSB given by N-1
    end

endmodule

ALU /ALU-N bit/alu_nbittest.v
module test_nbit_alu();

    parameter N = 4;

    reg [N-1:0] A, B;
    reg [2:0] opcode;

    wire [N-1:0] Result;
    wire C, S, V, Z;

    // Instantiate ALU
    alu_nbit #(N) uut (
        .A(A),
        .B(B),
        .opcode(opcode),
        .Result(Result),
        .C(C),
        .S(S),
        .V(V),
        .Z(Z)
    );

    initial begin
        $dumpfile("alu.vcd");
        $dumpvars(0, test_nbit_alu);

        // ADD
        A = 4'd5; B = 4'd3; opcode = 3'b000; #10;
        A = 4'd7; B = 4'd2; opcode = 3'b000; #10;

        // SUB
        A = 4'd5; B = 4'd3; opcode = 3'b001; #10;

        // AND
        A = 4'b1100; B = 4'b1010; opcode = 3'b010; #10;

        // OR
        A = 4'b1100; B = 4'b1010; opcode = 3'b011; #10;

        // XOR
        A = 4'b1100; B = 4'b1010; opcode = 3'b100; #10;

        // SHIFT
        A = 4'b0101; opcode = 3'b101; #10;

        // ARITH SHIFT
        A = 4'b1000; opcode = 3'b111; #10;

        $finish;
    end

endmodule

ALU /ALU-N bit/alu.vcd
$date
	Sun May  3 20:44:58 2026
$end
$version
	Icarus Verilog
$end
$timescale
	1s
$end
$scope module test_nbit_alu $end
$var wire 1 ! Z $end
$var wire 1 " V $end
$var wire 1 # S $end
$var wire 4 $ Result [3:0] $end
$var wire 1 % C $end
$var parameter 32 & N $end
$var reg 4 ' A [3:0] $end
$var reg 4 ( B [3:0] $end
$var reg 3 ) opcode [2:0] $end
$scope module uut $end
$var wire 4 * A [3:0] $end
$var wire 4 + B [3:0] $end
$var wire 4 , and_out [3:0] $end
$var wire 3 - opcode [2:0] $end
$var wire 4 . or_out [3:0] $end
$var wire 4 / xor_out [3:0] $end
$var wire 5 0 temp_sub [4:0] $end
$var wire 5 1 temp_add [4:0] $end
$var wire 4 2 sub_out [3:0] $end
$var wire 4 3 right_shift [3:0] $end
$var wire 4 4 left_shift [3:0] $end
$var wire 4 5 ar_shift [3:0] $end
$var wire 4 6 add_out [3:0] $end
$var parameter 32 7 N $end
$var reg 1 % C $end
$var reg 4 8 Result [3:0] $end
$var reg 1 # S $end
$var reg 1 " V $end
$var reg 1 ! Z $end
$upscope $end
$upscope $end
$enddefinitions $end
$comment Show the parameter values. $end
$dumpall
b100 7
b100 &
$end
#0
$dumpvars
b1000 8
b1000 6
b10 5
b1010 4
b10 3
b10 2
b1000 1
b10 0
b110 /
b111 .
b0 -
b1 ,
b11 +
b101 *
b0 )
b11 (
b101 '
0%
b1000 $
1#
1"
0!
$end
#10
b1001 $
b1001 8
b10 ,
b101 /
b1001 6
b101 2
1"
b1110 4
b11 3
b11 5
b10 (
b10 +
b1001 1
b101 0
b111 '
b111 *
#20
b1 ,
b110 /
b1000 6
b10 2
0#
b10 $
b10 8
0"
b1010 4
b10 3
b10 5
b1 )
b1 -
b11 (
b11 +
b1000 1
b10 0
b101 '
b101 *
#30
1#
b1000 ,
b1110 .
b110 6
b1000 $
b1000 8
b1000 4
b110 3
b1110 5
b10 )
b10 -
b1010 (
b1010 +
b10110 1
b10 0
b1100 '
b1100 *
#40
b1110 $
b1110 8
b11 )
b11 -
#50
0#
b110 $
b110 8
b100 )
b100 -
#60
b0 ,
b1111 .
b1111 /
b1111 6
b1011 2
1#
b1010 $
b1010 8
b1010 4
b10 3
b10 5
b101 )
b101 -
b1111 1
b11011 0
b101 '
b101 *
#70
b1000 ,
b1010 .
b10 /
b10 6
b1110 2
b1100 $
b1100 8
b0 4
b100 3
b1100 5
b111 )
b111 -
b10010 1
b11110 0
b1000 '
b1000 *
