CPU/Register File/Design /enable_nbit.sv
module enable_nbit #(parameter N=4)
(
 input logic clk,rst,en,
 input logic [N-1:0] Din,  //Parameterises D and Q and any N-bit 
 output logic [N-1:0] q
);

always_ff @(posedge clk)begin
if (rst)
  q<='0;
else if(en)
  q<=Din;

end
endmodule

Sequential circuits/Registers/N-bit enable register /nbittest.v
module nregister;

    parameter N = 4;

    logic clk;
    logic rst;
    logic en;
    logic [N-1:0] Din;
    logic [N-1:0] q;

    // DUT Device under test
    enable_nbit #(.N(N)) uut (
        .clk(clk),
        .rst(rst),
        .en(en),
        .Din(Din),
        .q(q)
    );

    // Clock Generation (10 ns period)
    initial begin
        clk = 0;
        forever #5 clk = ~clk;
    end

    // Waveform Dump
    initial begin
        $dumpfile("nregister.vcd");
        $dumpvars(0, nregister);
    end

    // Monitor
    initial begin
        $monitor("Time=%0t | rst=%b | en=%b | Din=%b | q=%b",
                  $time, rst, en, Din, q);
    end

    // Test Stimulus
    initial begin

        // Initialize
        rst = 1;
        en  = 0;
        Din = 4'b0000;

        // Apply reset
        #10;
        rst = 0;

        // Load first value
        en  = 1;
        Din = 4'b1001;
        #10;

        // Load second value
        Din = 4'b1101;
        #10;

        // Disable register (should HOLD previous value)
        en  = 0;
        Din = 4'b1111;
        #10;

        // Enable again (should now load 1111)
        en  = 1;
        #10;

        $finish;

    end

endmodule

Sequential circuits/Registers/N-bit enable register /nregister.vcd
$date
	Mon Jul 27 12:46:51 2026
$end
$version
	Icarus Verilog
$end
$timescale
	1s
$end
$scope module nregister $end
$var wire 4 ! q [3:0] $end
$var parameter 32 " N $end
$var reg 4 # Din [3:0] $end
$var reg 1 $ clk $end
$var reg 1 % en $end
$var reg 1 & rst $end
$scope module uut $end
$var wire 4 ' Din [3:0] $end
$var wire 1 $ clk $end
$var wire 1 % en $end
$var wire 1 & rst $end
$var parameter 32 ( N $end
$var reg 4 ) q [3:0] $end
$upscope $end
$upscope $end
$enddefinitions $end
$comment Show the parameter values. $end
$dumpall
b100 (
b100 "
$end
#0
$dumpvars
bx )
b0 '
1&
0%
0$
b0 #
bx !
$end
#5
b0 !
b0 )
1$
#10
0$
b1001 #
b1001 '
1%
0&
#15
b1001 !
b1001 )
1$
#20
0$
b1101 #
b1101 '
#25
b1101 !
b1101 )
1$
#30
0$
b1111 #
b1111 '
0%
#35
1$
#40
0$
1%
#45
b1111 !
b1111 )
1$
