Sequential circuits/Registers/Register 4 bit/pipo4bit.sv
module para4bit(
 input logic clk,rst,
 input logic [3:0]Din,
 output logic [3:0]q
);

always_ff @(posedge clk)begin
if(rst)
  q<=4'b0000;
else begin
  q[3]<=Din[3];
  q[2]<=Din[2];
  q[1]<=Din[1];
  q[0]<=Din[0];
end

end
endmodule

Sequential circuits/Registers/Register 4 bit/bit4test.v


module register;

    logic clk;
    logic rst;
    logic [3:0]Din;
    logic [3:0] q;

    // DUT
    para4bit uut(
        .clk(clk),
        .rst(rst),
        .Din(Din),
        .q(q)
    );

    // Clock Generation (10 ns period)
    initial begin
        clk = 0;
        forever #5 clk = ~clk;
    end

    // Waveform Dump
    initial begin
        $dumpfile("register.vcd");
        $dumpvars(0, register);
    end

    // Monitor Output
    initial begin
        $monitor("Time=%0t | rst=%b | Din=%b | q=%b",
                  $time, rst, Din, q);
    end

    // Test Stimulus
    initial begin

        // Initialize
        rst = 1;
        Din = 4'b0000;

        // Reset
        #10;
        rst = 0;

        // Shift in 1
        Din = 4'b1001;
        #10;

        // Shift in 0
        Din = 4'b1101;
        #10;

        // Shift in 1
        Din = 4'b1110;
        #10;

        // Shift in 1
        Din = 4'b1111;
        #10;

        $finish;

    end

endmodule

Sequential circuits/Registers/Register 4 bit/register.vcd
$date
	Sun Jul 26 19:54:15 2026
$end
$version
	Icarus Verilog
$end
$timescale
	1s
$end
$scope module register $end
$var wire 4 ! q [3:0] $end
$var reg 4 " Din [3:0] $end
$var reg 1 # clk $end
$var reg 1 $ rst $end
$scope module uut $end
$var wire 4 % Din [3:0] $end
$var wire 1 # clk $end
$var wire 1 $ rst $end
$var reg 4 & q [3:0] $end
$upscope $end
$upscope $end
$enddefinitions $end
$comment Show the parameter values. $end
$dumpall
$end
#0
$dumpvars
bx &
b0 %
1$
0#
b0 "
bx !
$end
#5
b0 !
b0 &
1#
#10
0#
b1001 "
b1001 %
0$
#15
b1001 !
b1001 &
1#
#20
0#
b1101 "
b1101 %
#25
b1101 !
b1101 &
1#
#30
0#
b1110 "
b1110 %
#35
b1110 !
b1110 &
1#
#40
0#
b1111 "
b1111 %
#45
b1111 !
b1111 &
1#
