CPU/Accumulator/Design/accu_reg.sv
module acc_reg #(parameter N=4)
(
 input logic clk,rst,accu_load,  //holds in the value
 input logic [N-1:0] alu_result,  //Parameterises ALU result
 output logic [N-1:0] accu_out   //Loads into the new value
);

always_ff @(posedge clk)begin
if (rst)
  accu_out<='0;
else if(accu_load)
  accu_out<=alu_result;

end
endmodule

CPU/Accumulator/Testbench and verification/tb_accu.sv
module testbench;

parameter N = 4;

logic clk;
logic rst;
logic accu_load;
logic [N-1:0] alu_result;
logic [N-1:0] accu_out;

// DUT (Device Under Test)
acc_reg #(.N(N)) uut (
    .clk(clk),
    .rst(rst),
    .accu_load(accu_load),
    .alu_result(alu_result),
    .accu_out(accu_out)
);

// Clock Generation (10 ns period)
initial begin
    clk = 0;
    forever #5 clk = ~clk;
end

// Waveform Dump
initial begin
    $dumpfile("acc_reg.vcd");
    $dumpvars(0, testbench);
end

// Monitor
initial begin
    $monitor("Time=%0t | rst=%b | accu_load=%b | alu_result=%b | accu_out=%b",
              $time, rst, accu_load, alu_result, accu_out);
end

// Test Stimulus
initial begin

    // Initialize
    rst = 1;
    accu_load = 0;
    alu_result = 4'b0000;

    // Apply Reset
    #10;
    rst = 0;

    // Load First ALU Result
    accu_load = 1;
    alu_result = 4'b1001;
    #10;

    // Load Second ALU Result
    alu_result = 4'b1101;
    #10;

    // Disable Loading (Should Hold Previous Value)
    accu_load = 0;
    alu_result = 4'b1111;
    #10;

    // Enable Loading Again (Should Load 1111)
    accu_load = 1;
    #10;

    $finish;

end

endmodule

CPU/Accumulator/Testbench and verification/acc_reg.vcd
$date
	Fri Aug  7 19:42:27 2026
$end
$version
	Icarus Verilog
$end
$timescale
	1s
$end
$scope module testbench $end
$var wire 4 ! accu_out [3:0] $end
$var parameter 32 " N $end
$var reg 1 # accu_load $end
$var reg 4 $ alu_result [3:0] $end
$var reg 1 % clk $end
$var reg 1 & rst $end
$scope module uut $end
$var wire 1 # accu_load $end
$var wire 4 ' alu_result [3:0] $end
$var wire 1 % clk $end
$var wire 1 & rst $end
$var parameter 32 ( N $end
$var reg 4 ) accu_out [3:0] $end
$upscope $end
$upscope $end
$enddefinitions $end
$comment Show the parameter values. $end
$dumpall
b100 (
b100 "
$end
#0
$dumpvars
bx )
b0 '
1&
0%
b0 $
0#
bx !
$end
#5
b0 !
b0 )
1%
#10
0%
b1001 $
b1001 '
1#
0&
#15
b1001 !
b1001 )
1%
#20
0%
b1101 $
b1101 '
#25
b1101 !
b1101 )
1%
#30
0%
b1111 $
b1111 '
0#
#35
1%
#40
0%
1#
#45
b1111 !
b1111 )
1%
